checkMyApp/__init__.py
checkMyApp/checkMyApp.py
checkMyApp-0.0.2.dist-info/DESCRIPTION.rst
checkMyApp-0.0.2.dist-info/METADATA
checkMyApp-0.0.2.dist-info/RECORD
checkMyApp-0.0.2.dist-info/WHEEL
checkMyApp-0.0.2.dist-info/entry_points.txt
checkMyApp-0.0.2.dist-info/metadata.json
checkMyApp-0.0.2.dist-info/top_level.txt
